terraback/__init__.py
terraback/_build_info.py
terraback/cli/__init__.py
terraback/cli/main.py
terraback/cli/aws/__init__.py
terraback/cli/aws/session.py
terraback/cli/aws/acm/__init__.py
terraback/cli/aws/acm/certificates.py
terraback/cli/aws/apigateway/__init__.py
terraback/cli/aws/apigateway/rest_apis.py
terraback/cli/aws/autoscaling/__init__.py
terraback/cli/aws/autoscaling/auto_scaling_groups.py
terraback/cli/aws/autoscaling/launch_configurations.py
terraback/cli/aws/autoscaling/scaling_policies.py
terraback/cli/aws/cloudfront/__init__.py
terraback/cli/aws/cloudfront/cache_policies.py
terraback/cli/aws/cloudfront/distributions.py
terraback/cli/aws/cloudfront/origin_access_controls.py
terraback/cli/aws/cloudfront/origin_request_policies.py
terraback/cli/aws/cloudwatch/__init__.py
terraback/cli/aws/cloudwatch/alarms.py
terraback/cli/aws/cloudwatch/dashboards.py
terraback/cli/aws/cloudwatch/log_groups.py
terraback/cli/aws/ec2/__init__.py
terraback/cli/aws/ec2/amis.py
terraback/cli/aws/ec2/instances.py
terraback/cli/aws/ec2/key_pairs.py
terraback/cli/aws/ec2/launch_templates.py
terraback/cli/aws/ec2/network_interfaces.py
terraback/cli/aws/ec2/snapshots.py
terraback/cli/aws/ec2/volumes.py
terraback/cli/aws/ecr/__init__.py
terraback/cli/aws/ecr/repositories.py
terraback/cli/aws/ecs/__init__.py
terraback/cli/aws/ecs/clusters.py
terraback/cli/aws/ecs/services.py
terraback/cli/aws/ecs/task_definitions.py
terraback/cli/aws/efs/__init__.py
terraback/cli/aws/efs/access_points.py
terraback/cli/aws/efs/file_systems.py
terraback/cli/aws/efs/mount_targets.py
terraback/cli/aws/eips/__init__.py
terraback/cli/aws/eips/addresses.py
terraback/cli/aws/elasticache/__init__.py
terraback/cli/aws/elasticache/memcached_clusters.py
terraback/cli/aws/elasticache/parameter_groups.py
terraback/cli/aws/elasticache/redis_clusters.py
terraback/cli/aws/elasticache/replication_groups.py
terraback/cli/aws/elasticache/subnet_groups.py
terraback/cli/aws/elb/__init__.py
terraback_community-0.2.7.dist-info/licenses/LICENSE
terraback_community-0.2.7.dist-info/METADATA
terraback_community-0.2.7.dist-info/WHEEL
terraback_community-0.2.7.dist-info/entry_points.txt
terraback_community-0.2.7.dist-info/top_level.txt
terraback_community-0.2.7.dist-info/RECORD
