Metadata-Version: 2.4
Name: terraback-community
Version: 0.2.7
Summary: Terraback: A tool for infrastructure scanning and backup.
Author: Your Name
Author-email: your.email@example.com
Classifier: Programming Language :: Python :: 3
Classifier: Operating System :: OS Independent
Requires-Python: >=3.8
License-File: LICENSE
Requires-Dist: boto3==1.38.21
Requires-Dist: botocore==1.38.21
Requires-Dist: azure-identity==1.15.0
Requires-Dist: azure-mgmt-resource==23.1.0
Requires-Dist: azure-mgmt-compute==31.0.0
Requires-Dist: azure-mgmt-network==27.0.0
Requires-Dist: azure-mgmt-storage==21.2.0
Requires-Dist: azure-mgmt-web==7.3.0
Requires-Dist: azure-mgmt-sql==3.0.1
Requires-Dist: azure-mgmt-keyvault==10.3.0
Requires-Dist: azure-mgmt-monitor==6.0.0
Requires-Dist: azure-core==1.30.0
Requires-Dist: google-cloud-compute==1.14.0
Requires-Dist: google-cloud-storage==2.10.0
Requires-Dist: google-cloud-resource-manager==1.10.0
Requires-Dist: google-auth==2.23.0
Requires-Dist: typer==0.15.4
Requires-Dist: click==8.1.8
Requires-Dist: rich==14.0.0
Requires-Dist: colorama==0.4.6
Requires-Dist: Pygments==2.19.1
Requires-Dist: Jinja2==3.1.6
Requires-Dist: MarkupSafe==3.0.2
Requires-Dist: requests
Requires-Dist: cryptography
Requires-Dist: paramiko
Requires-Dist: pyyaml
Requires-Dist: jmespath==1.0.1
Requires-Dist: markdown-it-py==3.0.0
Requires-Dist: mdurl==0.1.2
Requires-Dist: python-dateutil==2.9.0.post0
Requires-Dist: shellingham==1.5.4
Requires-Dist: six==1.17.0
Requires-Dist: typing_extensions==4.13.2
Requires-Dist: urllib3<2.0,>=1.26.0
Dynamic: author
Dynamic: author-email
Dynamic: classifier
Dynamic: description
Dynamic: description-content-type
Dynamic: license-file
Dynamic: requires-dist
Dynamic: requires-python
Dynamic: summary
